sems_portal_api/__init__.py
sems_portal_api/sems_auth.py
sems_portal_api/sems_charts.py
sems_portal_api/sems_home_wrapper.py
sems_portal_api/sems_plant_details.py
sems_portal_api/sems_region.py
sems_portal_api-0.1.1.dist-info/METADATA
sems_portal_api-0.1.1.dist-info/WHEEL
sems_portal_api-0.1.1.dist-info/licenses/LICENSE.md
sems_portal_api-0.1.1.dist-info/RECORD
