Metadata-Version: 2.1
Name: sems_portal_api
Version: 0.1.1
Summary: A small package that wraps a few of the SEMS Portal apis
Project-URL: Homepage, https://github.com/andrewgierens/sems_portal_api
Project-URL: Bug Tracker, https://github.com/andrewgierens/sems_portal_api/issues
Author-email: Andrew Gierens <apgierens@gmail.com>
License-File: LICENSE.md
Classifier: License :: OSI Approved :: GNU General Public License v3 (GPLv3)
Classifier: Operating System :: OS Independent
Classifier: Programming Language :: Python :: 3
Requires-Python: >=3.5
